slacki/__init__.py
slacki/examples.py
slacki/slacki.py
slacki/data/__init__.py
slacki/utils/__init__.py
slacki/utils/check_connection.py
slacki-1.1.1.dist-info/LICENSE
slacki-1.1.1.dist-info/METADATA
slacki-1.1.1.dist-info/WHEEL
slacki-1.1.1.dist-info/top_level.txt
slacki-1.1.1.dist-info/RECORD
