Metadata-Version: 2.1
Name: slacki
Version: 1.1.1
Summary: Python package slacki for reading and posting in slack groups.
Home-page: https://github.com/erdogant/slacki
Author: Erdogan Taskesen
Author-email: erdogant@gmail.com
License: UNKNOWN
Download-URL: https://github.com/erdogant/slacki/archive/1.1.1.tar.gz
Platform: UNKNOWN
Classifier: Programming Language :: Python :: 3
Classifier: License :: OSI Approved :: MIT License
Classifier: Operating System :: OS Independent
Requires-Python: >=3
Requires-Dist: slacker
Requires-Dist: SlackClient (==1.3.2)
Requires-Dist: numpy
Requires-Dist: wget
